<?xml version="1.0" encoding="UTF-8" standalone="no"?>
<Envelope xmlns="https://www.bcb.gov.br/pi/reda.016/1.3">
    <AppHdr>
        <Fr>
            <FIId>
                <FinInstnId>
                    <Othr>
                        <Id>00038166</Id>
                    </Othr>
                </FinInstnId>
            </FIId>
        </Fr>
        <To>
            <FIId>
                <FinInstnId>
                    <Othr>
                        <Id>99999010</Id>
                    </Othr>
                </FinInstnId>
            </FIId>
        </To>
        <BizMsgIdr>M0003816612345678901234567890123</BizMsgIdr>
        <MsgDefIdr>reda.016.spi.1.3</MsgDefIdr>
        <CreDt>2020-01-01T08:30:12.000Z</CreDt>
        <Sgntr/>
    </AppHdr>
    <Document>
        <PtyStsAdvc>
            <MsgHdr>
                <MsgId>M0003816612345678901234567890123</MsgId>
                <CreDtTm>2020-01-01T08:30:12.000Z</CreDtTm>
                <OrgnlBizInstr>
                    <MsgId>M9999901012345678901234567890123</MsgId>
                </OrgnlBizInstr>
            </MsgHdr>
            <PtySts>
                <Sts>QUED</Sts>
                <StsRsn>
                    <Rsn>
                        <Prtry>EXP5</Prtry>
                    </Rsn>
                </StsRsn>
            </PtySts>
        </PtyStsAdvc>
    </Document>
</Envelope>